decorators/__init__.py
decorators/example.py
walter_kit-0.0.2.dist-info/METADATA
walter_kit-0.0.2.dist-info/WHEEL
walter_kit-0.0.2.dist-info/top_level.txt
walter_kit-0.0.2.dist-info/RECORD
