Metadata-Version: 2.1
Name: walter-kit
Version: 0.0.2
Summary: Source code Repository
Home-page: https://github.com/ropering
Author: WalterO
Author-email: ropering.dev@gmail.com
License: UNKNOWN
Project-URL: Bug Tracker, https://github.com/ropering/issues
Platform: UNKNOWN
Classifier: Programming Language :: Python :: 3
Classifier: License :: OSI Approved :: MIT License
Classifier: Operating System :: OS Independent
Requires-Python: >=3.6
